cr/nimble/__init__.py
cr/nimble/affine.py
cr/nimble/compression.py
cr/nimble/data.py
cr/nimble/rq.py
cr/nimble/spd.py
cr/nimble/subspaces.py
cr/nimble/svd.py
cr/nimble/test_setup.py
cr/nimble/version.py
cr/nimble/_src/affine.py
cr/nimble/_src/array.py
cr/nimble/_src/chol.py
cr/nimble/_src/distance.py
cr/nimble/_src/dls.py
cr/nimble/_src/householder.py
cr/nimble/_src/latex.py
cr/nimble/_src/linear.py
cr/nimble/_src/matrix.py
cr/nimble/_src/metrics.py
cr/nimble/_src/ndarray.py
cr/nimble/_src/noise.py
cr/nimble/_src/norm.py
cr/nimble/_src/rq.py
cr/nimble/_src/signalcomparison.py
cr/nimble/_src/similarity.py
cr/nimble/_src/standard_matrices.py
cr/nimble/_src/subspaces.py
cr/nimble/_src/svd_utils.py
cr/nimble/_src/toeplitz.py
cr/nimble/_src/triangular.py
cr/nimble/_src/util.py
cr/nimble/_src/vector.py
cr/nimble/_src/compression/binary_arrs.py
cr/nimble/_src/compression/bits.py
cr/nimble/_src/compression/fixed_length.py
cr/nimble/_src/compression/run_length.py
cr/nimble/_src/data/subspaces.py
cr/nimble/_src/discrete/number.py
cr/nimble/_src/dsp/convolution.py
cr/nimble/_src/dsp/dct.py
cr/nimble/_src/dsp/energy.py
cr/nimble/_src/dsp/features.py
cr/nimble/_src/dsp/interpolation.py
cr/nimble/_src/dsp/quantization.py
cr/nimble/_src/dsp/scaling.py
cr/nimble/_src/dsp/sparse.py
cr/nimble/_src/dsp/spectrum.py
cr/nimble/_src/dsp/synthetic_signals.py
cr/nimble/_src/dsp/thresholding.py
cr/nimble/_src/dsp/util.py
cr/nimble/_src/dsp/wht.py
cr/nimble/_src/io/resource.py
cr/nimble/_src/io/sphinx.py
cr/nimble/_src/spd/jacobi.py
cr/nimble/_src/svdpack/bdsqr.py
cr/nimble/_src/svdpack/lanbpro.py
cr/nimble/_src/svdpack/lanbpro_utils.py
cr/nimble/_src/svdpack/lansvd.py
cr/nimble/_src/svdpack/lansvd_utils.py
cr/nimble/_src/svdpack/reorth.py
cr/nimble/dsp/__init__.py
cr/nimble/dsp/signals.py
cr/nimble/io/__init__.py
cr/nimble/io/resource.py
cr_nimble-0.4.0.dist-info/LICENSE
cr_nimble-0.4.0.dist-info/METADATA
cr_nimble-0.4.0.dist-info/WHEEL
cr_nimble-0.4.0.dist-info/entry_points.txt
cr_nimble-0.4.0.dist-info/top_level.txt
cr_nimble-0.4.0.dist-info/RECORD
