Metadata-Version: 2.1
Name: cr-nimble
Version: 0.4.0
Summary: Iterative algorithms for numerical linear algebra with JAX
Home-page: https://carnotresearch.github.io/cr-nimble
Author: CR-Suite Development Team
Author-email: contact@carnotresearch.com
License: Apache 2.0: http://www.apache.org/licenses/LICENSE-2.0
Download-URL: https://github.com/carnotresearch/cr-nimble/archive/v0.4.0.tar.gz
Project-URL: Issue Tracker, https://github.com/carnotresearch/cr-nimble/issues
Keywords: Linear Algebra
Platform: UNKNOWN
Classifier: Development Status :: 3 - Alpha
Classifier: Intended Audience :: Developers
Classifier: Topic :: Multimedia
Classifier: Topic :: Multimedia :: Video
Classifier: Topic :: Scientific/Engineering :: Image Processing
Classifier: Topic :: Scientific/Engineering :: Image Recognition
Classifier: License :: OSI Approved :: Apache Software License
Classifier: Operating System :: Unix
Classifier: Operating System :: POSIX
Classifier: Programming Language :: Python :: 3.8
Classifier: Programming Language :: Python :: 3.9
Classifier: Programming Language :: Python :: 3.10
Classifier: Programming Language :: Python :: Implementation :: CPython
Requires-Python: >=3.8
Requires-Dist: numpy >=1.24
Requires-Dist: scipy >=1.10
Requires-Dist: pandas >=1.0.0
Requires-Dist: matplotlib >=3.7
Requires-Dist: pandas >=2.0
Requires-Dist: requests >=2.31
Requires-Dist: sympy >=1.12
Requires-Dist: bitarray >=2.8
Requires-Dist: jax >=0.4.3
Requires-Dist: jaxlib >=0.4.3
Provides-Extra: dev
Provides-Extra: test
Requires-Dist: pytest ; extra == 'test'
Requires-Dist: pytest-cov ; extra == 'test'
